probs_system/build/lib/probs_system/build/lib/probs_system/build/lib/probs_system/tests/conftest.py
probs_system/build/lib/probs_system/build/lib/probs_system/build/lib/probs_system/tests/test_endpoint.py
probs_system/build/lib/probs_system/build/lib/probs_system/tests/conftest.py
probs_system/build/lib/probs_system/build/lib/probs_system/tests/test_endpoint.py
probs_system/build/lib/probs_system/tests/conftest.py
probs_system/build/lib/probs_system/tests/test_endpoint.py
probs_system/data/README.md
probs_system/scripts/endpoint/input.rdfox
probs_system/scripts/endpoint/load_data.rdfox
probs_system/scripts/endpoint/load_rules.rdfox
probs_system/scripts/endpoint/master.rdfox
probs_system/scripts/endpoint/process.rdfox
probs_system/scripts/endpoint/rules.dlog
probs_system/scripts/endpoint/set_prefixes.rdfox
probs_system/scripts/endpoint/setup-RDFox.rdfox
probs_system/scripts/endpoint/arguments/param_.rdfox
probs_system/scripts/endpoint/arguments/param_endpoint.port.rdfox
probs_system/scripts/endpoint/arguments/process_args.rdfox
probs_system/tests/conftest.py
probs_system/tests/test_endpoint.py
probs_module_endpoint-2.0.0.dist-info/LICENSE
probs_module_endpoint-2.0.0.dist-info/METADATA
probs_module_endpoint-2.0.0.dist-info/WHEEL
probs_module_endpoint-2.0.0.dist-info/top_level.txt
probs_module_endpoint-2.0.0.dist-info/RECORD
