Metadata-Version: 2.1
Name: probs_module_endpoint
Version: 2.0.0
Summary: Endpoint (reasoning) RDFox scripts for the PRObs system
Author: Stefano Germano, Rick Lupton, Carla Saunders, Stephen Boyle
License-File: LICENSE
Requires-Dist: probs-module-ontology ==2.0.0
